pypiexperiment/.DS_Store
pypiexperiment/3.EXECUTE_ME.py
pypiexperiment/GAUSS_INT.py
pypiexperiment/GENERA_POLY.py
pypiexperiment/INT_SYMP.py
pypiexperiment/INT_SYMP_PV.py
pypiexperiment/MC_analisi.py
pypiexperiment/METAFUNC.py
pypiexperiment/METAPOLY.py
pypiexperiment/ROOTFINDER.py
pypiexperiment/SELETTORE_FUNC.py
pypiexperiment/SELETTORE_POLY.py
pypiexperiment/__init__.py
pypiexperiment/example.py
pypiexperiment/fractal_zoom.py
pypiexperiment/mc_integral_1_dim.py
pypiexperiment/nr.py
pypiexperiment/qtrap.py
pypiexperiment/rosignoli_lib.py
pypiexperiment/third.py
pypiexperiment/trapzd.py
pypiexperiment/zeros.py
pypiexperiment-0.0.1.dist-info/METADATA
pypiexperiment-0.0.1.dist-info/WHEEL
pypiexperiment-0.0.1.dist-info/licenses/LICENSE
pypiexperiment-0.0.1.dist-info/RECORD
