Metadata-Version: 2.1
Name: pypiexperiment
Version: 0.0.1
Summary: This package is full of important physical utilities written by me.
Project-URL: Homepage, https://github.com/ImanetorX98/Physics-utility
Project-URL: Bug Tracker, https://github.com/pypa/sampleproject/issues
Author-email: Iman Rosignoli <iman.rosignoli@gmail.com>
License-File: LICENSE
Classifier: License :: OSI Approved :: MIT License
Classifier: Operating System :: OS Independent
Classifier: Programming Language :: Python :: 3
Requires-Python: >=3.7
